LICENSE
MANIFEST.in
README.rst
gfm.py
setup.py
test_gfm.py
gfm.egg-info/PKG-INFO
gfm.egg-info/SOURCES.txt
gfm.egg-info/dependency_links.txt
gfm.egg-info/requires.txt
gfm.egg-info/top_level.txt