Metadata-Version: 1.1
Name: gfm
Version: 0.0.1
Summary: Convert GitHub-Flavored Markdown to HTML
Home-page: http://github.com/stewart/gfm/
Author: Andrew Stewart
Author-email: andrew@stwrt.ca
License: Copyright (c) 2013 Andrew Stewart
